liquid/__init__.py
liquid/defaults.py
liquid/exts/__init__.py
liquid/exts/ext.py
liquid/exts/filter_colon.py
liquid/exts/front_matter.py
liquid/exts/jekyll.py
liquid/exts/shopify.py
liquid/exts/standard.py
liquid/exts/wild.py
liquid/filters/__init__.py
liquid/filters/jekyll.py
liquid/filters/manager.py
liquid/filters/shopify.py
liquid/filters/standard.py
liquid/filters/wild.py
liquid/liquid.py
liquid/patching.py
liquid/tags/__init__.py
liquid/tags/jekyll.py
liquid/tags/manager.py
liquid/tags/shopify.py
liquid/tags/standard.py
liquid/tags/wild.py
liquid/utils.py
liquidpy-0.8.6.dist-info/METADATA
liquidpy-0.8.6.dist-info/WHEEL
liquidpy-0.8.6.dist-info/licenses/LICENSE
liquidpy-0.8.6.dist-info/RECORD
